{"hands_on_practices": [{"introduction": "要掌握计算接触力学，第一步是理解在单个点上如何实施摩擦定律。本练习 [@problem_id:3537748] 提供了一个具体的起点，用于理解摩擦接触模型。它演示了如何在单个积分点应用库仑摩擦的基本 Karush-Kuhn-Tucker (KKT) 条件，以区分粘着（stick）和滑动（slip）状态，并计算校正后的接触牵引力。", "problem": "在一个弹性体和刚性障碍物之间的粗糙摩擦接触界面上，一个积分点的约束通过拉格朗日乘子施加。不可穿透约束由法向拉格朗日乘子 $\\lambda_{n}$ 表示，无滑移/摩擦约束由切向拉格朗日乘子向量 $\\boldsymbol{\\lambda}_{t}$ 表示，接触牵引力定义为 $\\mathbf{t}_{c}=\\lambda_{n}\\mathbf{n}+\\boldsymbol{\\lambda}_{t}$，其中 $\\mathbf{n}$ 是指向障碍物外部的单位法向量。该界面遵循库仑摩擦定律。使用基本的法向和摩擦锥互补结构作为出发点：(i) 法向互补性 $g_{n}\\ge 0$, $\\lambda_{n}\\ge 0$, $g_{n}\\lambda_{n}=0$，其中 $g_{n}$ 是法向间隙；(ii) 摩擦锥容许性 $\\|\\boldsymbol{\\lambda}_{t}\\|\\le \\mu\\,\\lambda_{n}$，其中 $\\mu0$，以及与此锥面相关的、控制粘滞与滑移之间转换的 Karush–Kuhn–Tucker (KKT) 开关条件。\n\n在一个准静态增量步结束时，假设法向接触处于激活状态且间隙为零，该点的局部正交归一基的单位法向量为 $\\mathbf{n}=(0,1,0)$，切平面与 $\\mathbf{n}$ 正交，摩擦系数为 $\\mu=0.35$，法向拉格朗日乘子为 $\\lambda_{n}=120\\,\\mathrm{kPa}$，并且在全局坐标系下表示的粘滞预测（试探）切向拉格朗日乘子为 $\\boldsymbol{\\lambda}_{t}^{\\mathrm{tr}}=(50,\\,0,\\,70)\\,\\mathrm{kPa}$。从上述互补框架出发，不调用任何预先给定的投影公式，判断该点是处于粘滞还是滑移状态，相应地施加锥面互补条件，并计算修正后的 $\\boldsymbol{\\lambda}_{t}$ 和最终的接触牵引力 $\\mathbf{t}_{c}$。\n\n最后，报告接触牵引力大小 $\\|\\mathbf{t}_{c}\\|$，单位为 $\\mathrm{kPa}$。将您的答案四舍五入到4位有效数字。以 $\\mathrm{kPa}$ 为单位表示最终结果。", "solution": "该问题要求分析在准静态加载增量步下，摩擦界面上单个接触点的状态。约束的施加基于库仑摩擦框架下的拉格朗日乘子法。必须确定接触点的状态（粘滞或滑移），并计算最终的接触牵引力。整个过程遵循接触问题的 Karush–Kuhn–Tucker (KKT) 互补条件。\n\n已知条件如下：\n障碍物表面的单位法向量为 $\\mathbf{n} = (0, 1, 0)$。\n摩擦系数为 $\\mu = 0.35$。\n代表法向接触压力的法向拉格朗日乘子为 $\\lambda_{n} = 120\\,\\mathrm{kPa}$。题目说明法向接触处于激活状态 ($g_{n}=0$)，并且由于 $\\lambda_{n}  0$，法向互补条件 $g_{n}\\lambda_{n}=0$ 得以满足。\n粘滞预测（试探）切向拉格朗日乘子为 $\\boldsymbol{\\lambda}_{t}^{\\mathrm{tr}} = (50, 0, 70)\\,\\mathrm{kPa}$。\n\n问题的核心在于摩擦锥约束，该约束规定，一个点要处于物理上容许的状态，其切向牵引力的大小 $\\|\\boldsymbol{\\lambda}_{t}\\|$ 不能超过库仑摩擦定律所允许的最大值 $\\mu \\lambda_{n}$。这表示为：\n$$ \\|\\boldsymbol{\\lambda}_{t}\\| \\le \\mu \\lambda_{n} $$\n\n接触力学的计算流程通常采用预测-校正方案。我们首先假设该点处于粘滞状态（预测步），并计算一个试探切向牵引力 $\\boldsymbol{\\lambda}_{t}^{\\mathrm{tr}}$。然后，我们通过对照摩擦锥约束来检验该试探状态是否容许。\n\n步骤1：检查该点是处于粘滞还是滑移状态。\n粘滞的条件是 $\\|\\boldsymbol{\\lambda}_{t}^{\\mathrm{tr}}\\| \\le \\mu \\lambda_{n}$。如果此条件被违反，则该点处于滑移状态。\n\n我们来计算试探切向拉格朗日乘子的大小：\n$$ \\|\\boldsymbol{\\lambda}_{t}^{\\mathrm{tr}}\\| = \\sqrt{50^2 + 0^2 + 70^2} = \\sqrt{2500 + 4900} = \\sqrt{7400}\\,\\mathrm{kPa} $$\n其数值约为 $\\|\\boldsymbol{\\lambda}_{t}^{\\mathrm{tr}}\\| \\approx 86.023\\,\\mathrm{kPa}$。\n\n接下来，我们计算最大容许切向牵引力（摩擦极限）：\n$$ \\mu \\lambda_{n} = 0.35 \\times 120\\,\\mathrm{kPa} = 42\\,\\mathrm{kPa} $$\n\n现在，我们比较这两个值：\n$$ \\sqrt{7400}\\,\\mathrm{kPa}  42\\,\\mathrm{kPa} $$\n由于 $\\|\\boldsymbol{\\lambda}_{t}^{\\mathrm{tr}}\\|  \\mu \\lambda_{n}$，试探状态是不可容许的。粘滞的假设是错误的，该点必定处于滑移状态。\n\n步骤2：施加滑移条件（校正步）。\n对于处于滑移状态的点，切向牵引力必须位于摩擦锥的边界上。这意味着其大小必须恰好等于摩擦极限，并且其方向必须与相对切向运动的方向相反。在这个率无关塑性类比中，修正后的切向牵引力 $\\boldsymbol{\\lambda}_{t}$ 的方向与试探牵引力 $\\boldsymbol{\\lambda}_{t}^{\\mathrm{tr}}$ 的方向共线。这被称为径向返回算法。\n\n修正后的切向拉格朗日乘子 $\\boldsymbol{\\lambda}_{t}$ 是通过将试探向量 $\\boldsymbol{\\lambda}_{t}^{\\mathrm{tr}}$ 缩放回摩擦锥的表面得到的：\n$$ \\boldsymbol{\\lambda}_{t} = (\\mu \\lambda_{n}) \\frac{\\boldsymbol{\\lambda}_{t}^{\\mathrm{tr}}}{\\|\\boldsymbol{\\lambda}_{t}^{\\mathrm{tr}}\\|} $$\n代入数值：\n$$ \\boldsymbol{\\lambda}_{t} = 42 \\frac{(50, 0, 70)}{\\sqrt{7400}} = \\frac{42}{\\sqrt{7400}}(50, 0, 70)\\,\\mathrm{kPa} $$\n根据构造，这个修正后向量的大小为 $\\|\\boldsymbol{\\lambda}_t\\| = 42\\,\\mathrm{kPa}$。\n\n步骤3：计算总接触牵引力向量 $\\mathbf{t}_{c}$。\n总接触牵引力是其法向和切向分量的和：\n$$ \\mathbf{t}_{c} = \\lambda_{n}\\mathbf{n} + \\boldsymbol{\\lambda}_{t} $$\n代入向量和标量：\n$$ \\mathbf{t}_{c} = 120(0, 1, 0) + \\frac{42}{\\sqrt{7400}}(50, 0, 70) $$\n$$ \\mathbf{t}_{c} = \\left( \\frac{2100}{\\sqrt{7400}}, 120, \\frac{2940}{\\sqrt{7400}} \\right)\\,\\mathrm{kPa} $$\n\n步骤4：计算总接触牵引力的大小 $\\|\\mathbf{t}_{c}\\|$。\n总接触牵引力的大小可以由其分量计算得出。然而，一个更直接的方法是认识到法向分量 $\\lambda_{n}\\mathbf{n}$ 和切向分量 $\\boldsymbol{\\lambda}_{t}$ 是正交的。\n法向分量向量为 $\\lambda_{n}\\mathbf{n} = (0, 120, 0)$。\n切向分量向量 $\\boldsymbol{\\lambda}_{t}$ 的分量仅在 x-z 平面内，即 $\\boldsymbol{\\lambda}_{t} = (\\lambda_{t,x}, 0, \\lambda_{t,z})$。\n它们的点积为 $\\lambda_{n}\\mathbf{n} \\cdot \\boldsymbol{\\lambda}_{t} = (0)( \\lambda_{t,x}) + (120)(0) + (0)(\\lambda_{t,z}) = 0$。\n由于向量是正交的，我们可以对其向量和使用勾股定理：\n$$ \\|\\mathbf{t}_{c}\\|^2 = \\|\\lambda_{n}\\mathbf{n}\\|^2 + \\|\\boldsymbol{\\lambda}_{t}\\|^2 $$\n我们有：\n$\\|\\lambda_{n}\\mathbf{n}\\| = \\lambda_{n}\\|\\mathbf{n}\\| = \\lambda_{n} \\times 1 = 120\\,\\mathrm{kPa}$。\n$\\|\\boldsymbol{\\lambda}_{t}\\| = \\mu \\lambda_{n} = 42\\,\\mathrm{kPa}$ （根据滑移条件）。\n\n将这些大小代入勾股关系式：\n$$ \\|\\mathbf{t}_{c}\\|^2 = (120)^2 + (42)^2 = 14400 + 1764 = 16164 $$\n$$ \\|\\mathbf{t}_{c}\\| = \\sqrt{16164}\\,\\mathrm{kPa} $$\n计算其数值：\n$$ \\|\\mathbf{t}_{c}\\| \\approx 127.1377209\\,\\mathrm{kPa} $$\n题目要求将最终答案四舍五入到4位有效数字。\n$$ \\|\\mathbf{t}_{c}\\| \\approx 127.1\\,\\mathrm{kPa} $$", "answer": "$$\n\\boxed{127.1}\n$$", "id": "3537748"}, {"introduction": "在应用了粘滑判据之后，一个自然的问题是：这个判据背后的算法是如何从基本原理中推导出来的？本练习 [@problem_id:3537768] 将引导您从第一性原理推导“返回映射”算法，展示其如何源于最大耗散原理，并等价于一个最近点投影问题。这个实践连接了抽象的接触理论与有限元软件中使用的核心数值算法。", "problem": "考虑一个可变形体受压于刚性障碍物的三维小变形有限元法 (FEM) 离散化中的单个活动接触点。设法向拉格朗日乘子为 $\\lambda_{n}$（压缩为正），切向拉格朗日乘子为 $\\boldsymbol{\\lambda}_{t} \\in \\mathbb{R}^{2}$，在附着于接触面的固定标准正交切向标架 $\\{\\mathbf{t}_{1},\\mathbf{t}_{2}\\}$ 中表示。假设为摩擦系数为 $\\mu$ 的库仑摩擦，因此 $\\boldsymbol{\\lambda}_{t}$ 的容许集为摩擦锥截面（圆盘）$\\mathcal{F}=\\{\\boldsymbol{\\lambda}_{t} \\in \\mathbb{R}^{2}:\\|\\boldsymbol{\\lambda}_{t}\\| \\le \\mu \\lambda_{n},\\, \\lambda_{n} \\ge 0\\}$。接触点处的增量切向相对位移为 $\\Delta \\mathbf{u}_{t} \\in \\mathbb{R}^{2}$，它通过运动学映射 $\\Delta \\mathbf{u}_{t} = \\mathbf{B}_{t}\\,\\Delta \\mathbf{u}$ 与两个相互作用节点 $\\mathrm{P}$ 和 $\\mathrm{Q}$ 的增量全局位移向量 $\\Delta \\mathbf{u} \\in \\mathbb{R}^{6}$ 相关联，其中接触算子 $\\mathbf{B}_{t} \\in \\mathbb{R}^{2 \\times 6}$ 是已知的。在原始-对偶格式中，对全局平衡残差的接触贡献具有 $\\mathbf{B}_{t}^{T}\\boldsymbol{\\lambda}_{t}$ 的形式。\n\n仅使用 (i) 库仑摩擦锥 $\\mathcal{F}$，(ii) 率无关摩擦的最大耗散原理，以及 (iii) 针对由正常数 $k_{t}$ 控制切向滑移二次正则化的增广格式中增量拉格朗日量的平稳性，从第一性原理推导出一个回映算法，该算法根据已知的上一时刻乘子 $\\boldsymbol{\\lambda}_{t}^{n}$ 和给定的试探切向滑移 $\\Delta \\mathbf{u}_{t}$，在单个时间增量步内更新 $\\boldsymbol{\\lambda}_{t}$。你的推导必须从为固定 $\\lambda_{n}$ 下的切向接触子问题建立适当的约束最小化问题开始，并证明该算法等价于将试探乘子 $\\boldsymbol{\\lambda}_{t}^{\\mathrm{tr}}$ 投影到容许集 $\\mathcal{F}$ 上的最近点投影。然后，说明更新后的 $\\boldsymbol{\\lambda}_{t}$ 如何通过接触残差项 $\\mathbf{B}_{t}^{T}\\boldsymbol{\\lambda}_{t}$ 与全局 Newton 系统耦合。\n\n最后，根据以下具体数据评估推导出的公式，并提供最终得到的全局接触力向量 $\\mathbf{B}_{t}^{T}\\boldsymbol{\\lambda}_{t}$ 作为你的最终答案。使用全局自由度排序 $\\Delta \\mathbf{u} = \\big(u_{\\mathrm{P}x},\\,u_{\\mathrm{P}y},\\,u_{\\mathrm{P}z},\\,u_{\\mathrm{Q}x},\\,u_{\\mathrm{Q}y},\\,u_{\\mathrm{Q}z}\\big)^{T}$，并取切向标架与全局坐标轴对齐，以便\n$$\n\\mathbf{B}_{t}=\\begin{pmatrix}\n1  0  0  -1  0  0\\\\\n0  1  0  0  -1  0\n\\end{pmatrix}.\n$$\n假设 $\\boldsymbol{\\lambda}_{t}^{n}=\\mathbf{0}$，$\\lambda_{n}=20000\\,\\text{N}$，$\\mu=0.3$，$k_{t}=1.0\\times 10^{7}\\,\\text{N/m}$ 以及 $\\Delta \\mathbf{u}_{t}=\\begin{pmatrix}0.0008\\\\-0.0006\\end{pmatrix}\\,\\text{m}$。将最终答案表示为 $\\mathbf{B}_{t}^{T}\\boldsymbol{\\lambda}_{t}$ 的6分量行向量，单位为 $\\text{N}$。无需四舍五入；请提供由计算确定的精确值。", "solution": "该问题要求在小变形、三维有限元接触设置中，为库仑摩擦推导一个回映算法。推导必须基于第一性原理，包括最大耗散和增广拉格朗日格式。必须证明其与最近点投影的等价性。最后，将推导出的算法应用于一个具体的数值算例。\n\n推导从考虑单个接触点的局部切向接触问题开始。状态由切向拉格朗日乘子 $\\boldsymbol{\\lambda}_t \\in \\mathbb{R}^2$ 描述，它代表摩擦牵引力。\n\n**1. 率无关摩擦的本构关系**\n\n率无关塑性和摩擦的基本假设是，将总增量相对位移（滑移）$\\Delta\\mathbf{u}_t$ 分解为一个弹性（可逆）部分 $\\Delta\\mathbf{u}_t^e$ 和一个塑性（不可逆）部分 $\\Delta\\mathbf{u}_t^p$：\n$$\n\\Delta\\mathbf{u}_t = \\Delta\\mathbf{u}_t^e + \\Delta\\mathbf{u}_t^p\n$$\n问题指定了一个带有二次正则化参数 $k_t$ 的增广格式。该参数将切向牵引力的变化与滑移的弹性部分联系起来，为接触界面定义了一个虚拟的弹性行为：\n$$\n\\boldsymbol{\\lambda}_t - \\boldsymbol{\\lambda}_t^n = k_t \\Delta\\mathbf{u}_t^e\n$$\n其中 $\\boldsymbol{\\lambda}_t^n$ 是增量步开始时的牵引力。这可以重写为：\n$$\n\\Delta\\mathbf{u}_t^e = \\frac{1}{k_t}(\\boldsymbol{\\lambda}_t - \\boldsymbol{\\lambda}_t^n)\n$$\n塑性滑移 $\\Delta\\mathbf{u}_t^p$ 由最大耗散原理支配。对于容许牵引力集 $\\mathcal{F} = \\{\\boldsymbol{\\tau} \\in \\mathbb{R}^2 : \\|\\boldsymbol{\\tau}\\| \\le \\mu\\lambda_n\\}$，该原理导出一个法向法则。设摩擦屈服函数为 $\\phi(\\boldsymbol{\\lambda}_t) = \\|\\boldsymbol{\\lambda}_t\\| - \\mu\\lambda_n$。法向法则指出，塑性滑移向量必须垂直于屈服面：\n$$\n\\Delta\\mathbf{u}_t^p = \\gamma \\frac{\\partial \\phi}{\\partial \\boldsymbol{\\lambda}_t} = \\gamma \\frac{\\boldsymbol{\\lambda}_t}{\\|\\boldsymbol{\\lambda}_t\\|}\n$$\n其中 $\\gamma \\ge 0$ 是一致性参数或塑性滑移乘子。此关系受约束优化的 Karush-Kuhn-Tucker (KKT) 条件约束：\n$$\n\\phi(\\boldsymbol{\\lambda}_t) \\le 0, \\quad \\gamma \\ge 0, \\quad \\gamma \\phi(\\boldsymbol{\\lambda}_t) = 0\n$$\n这些条件强制执行粘滑逻辑：如果牵引力严格位于摩擦锥内部（$\\phi  0$），则没有塑性滑移（$\\gamma = 0$）。如果存在塑性滑移（$\\gamma > 0$），则牵引力必须位于摩擦锥的边界上（$\\phi = 0$）。\n\n**2. 回映算法的推导**\n\n将 $\\Delta\\mathbf{u}_t^e$ 和 $\\Delta\\mathbf{u}_t^p$ 的表达式代入滑移分解中，我们得到 $\\boldsymbol{\\lambda}_t$ 的单个演化方程：\n$$\n\\Delta\\mathbf{u}_t = \\frac{1}{k_t}(\\boldsymbol{\\lambda}_t - \\boldsymbol{\\lambda}_t^n) + \\gamma \\frac{\\boldsymbol{\\lambda}_t}{\\|\\boldsymbol{\\lambda}_t\\|}\n$$\n为了求解 $\\boldsymbol{\\lambda}_t$，我们首先定义一个 **试探状态**。试探状态是基于纯弹性行为（粘滞，$\\gamma=0$）假设的预测值。\n$$\n\\Delta\\mathbf{u}_t^p = \\mathbf{0} \\implies \\Delta\\mathbf{u}_t = \\Delta\\mathbf{u}_t^e = \\frac{1}{k_t}(\\boldsymbol{\\lambda}_t^{\\mathrm{tr}} - \\boldsymbol{\\lambda}_t^n)\n$$\n这给出了试探切向牵引力 $\\boldsymbol{\\lambda}_t^{\\mathrm{tr}}$ 的定义：\n$$\n\\boldsymbol{\\lambda}_t^{\\mathrm{tr}} := \\boldsymbol{\\lambda}_t^n + k_t \\Delta\\mathbf{u}_t\n$$\n试探状态是一个已知量，因为 $\\boldsymbol{\\lambda}_t^n$、 $k_t$ 和试探滑移 $\\Delta\\mathbf{u}_t$ 在该增量步中是给定的。现在，我们检查这个试探状态是否容许。\n\n**情况1：粘滞条件** (`\\|\\boldsymbol{\\lambda}_t^{\\mathrm{tr}}\\| \\le \\mu\\lambda_n`)\n如果试探牵引力位于摩擦锥内部或其边界上，则 $\\phi(\\boldsymbol{\\lambda}_t^{\\mathrm{tr}}) \\le 0$。我们关于 $\\gamma=0$ 的假设与 KKT 条件一致。因此，试探状态就是最终的更新状态：\n$$\n\\boldsymbol{\\lambda}_t = \\boldsymbol{\\lambda}_t^{\\mathrm{tr}}\n$$\n\n**情况2：滑移条件** (`\\|\\boldsymbol{\\lambda}_t^{\\mathrm{tr}}\\|  \\mu\\lambda_n`)\n如果试探牵引力位于摩擦锥外部，即 $\\phi(\\boldsymbol{\\lambda}_t^{\\mathrm{tr}})  0$，则弹性假设无效。必须发生塑性滑移（$\\gamma  0$），并且最终状态必须位于屈服面上（$\\phi(\\boldsymbol{\\lambda}_t) = 0$，因此 $\\|\\boldsymbol{\\lambda}_t\\| = \\mu\\lambda_n$）。\n\n我们使用演化方程将最终状态 $\\boldsymbol{\\lambda}_t$ 与试探状态 $\\boldsymbol{\\lambda}_t^{\\mathrm{tr}}$ 联系起来：\n$$\nk_t \\Delta\\mathbf{u}_t = \\boldsymbol{\\lambda}_t - \\boldsymbol{\\lambda}_t^n + k_t \\gamma \\frac{\\boldsymbol{\\lambda}_t}{\\|\\boldsymbol{\\lambda}_t\\|}\n$$\n代入 $\\boldsymbol{\\lambda}_t^{\\mathrm{tr}} = \\boldsymbol{\\lambda}_t^n + k_t \\Delta\\mathbf{u}_t$：\n$$\n\\boldsymbol{\\lambda}_t^{\\mathrm{tr}} - \\boldsymbol{\\lambda}_t^n = \\boldsymbol{\\lambda}_t - \\boldsymbol{\\lambda}_t^n + k_t \\gamma \\frac{\\boldsymbol{\\lambda}_t}{\\|\\boldsymbol{\\lambda}_t\\|} \\implies \\boldsymbol{\\lambda}_t^{\\mathrm{tr}} = \\boldsymbol{\\lambda}_t + k_t \\gamma \\frac{\\boldsymbol{\\lambda}_t}{\\|\\boldsymbol{\\lambda}_t\\|}\n$$\n由于 $\\|\\boldsymbol{\\lambda}_t\\| = \\mu\\lambda_n$，这变为：\n$$\n\\boldsymbol{\\lambda}_t^{\\mathrm{tr}} = \\boldsymbol{\\lambda}_t \\left(1 + \\frac{k_t \\gamma}{\\mu\\lambda_n}\\right)\n$$\n该方程表明 $\\boldsymbol{\\lambda}_t$ 与 $\\boldsymbol{\\lambda}_t^{\\mathrm{tr}}$ 共线且方向相同。因此，我们可以写出：\n$$\n\\frac{\\boldsymbol{\\lambda}_t}{\\|\\boldsymbol{\\lambda}_t\\|} = \\frac{\\boldsymbol{\\lambda}_t^{\\mathrm{tr}}}{\\|\\boldsymbol{\\lambda}_t^{\\mathrm{tr}}\\|}\n$$\n更新后的牵引力 $\\boldsymbol{\\lambda}_t$ 是通过将试探牵引力向量缩放回屈服面得到的。由于 $\\|\\boldsymbol{\\lambda}_t\\| = \\mu\\lambda_n$：\n$$\n\\boldsymbol{\\lambda}_t = (\\mu\\lambda_n) \\frac{\\boldsymbol{\\lambda}_t^{\\mathrm{tr}}}{\\|\\boldsymbol{\\lambda}_t^{\\mathrm{tr}}\\|}\n$$\n这个操作被称为径向回映或回映算法。\n\n**3. 与最近点投影的等价性**\n\n问题要求证明该算法等价于在容许集 $\\mathcal{F}$ 中找到距离试探牵引力 $\\boldsymbol{\\lambda}_t^{\\mathrm{tr}}$ 最近的点。这是一个约束优化问题：\n$$\n\\text{minimize} \\quad f(\\boldsymbol{\\tau}) = \\frac{1}{2} \\|\\boldsymbol{\\tau} - \\boldsymbol{\\lambda}_t^{\\mathrm{tr}}\\|^2 \\quad \\text{subject to} \\quad g(\\boldsymbol{\\tau}) = \\|\\boldsymbol{\\tau}\\| - \\mu\\lambda_n \\le 0\n$$\n这个问题的拉格朗日函数是 $\\mathcal{L}(\\boldsymbol{\\tau}, \\gamma_p) = \\frac{1}{2} \\|\\boldsymbol{\\tau} - \\boldsymbol{\\lambda}_t^{\\mathrm{tr}}\\|^2 + \\gamma_p (\\|\\boldsymbol{\\tau}\\| - \\mu\\lambda_n)$，其中 $\\gamma_p$ 是一个拉格朗日乘子。KKT 最优性条件是：\n1. 平稳性：$\\nabla_{\\boldsymbol{\\tau}} \\mathcal{L} = \\boldsymbol{\\tau} - \\boldsymbol{\\lambda}_t^{\\mathrm{tr}} + \\gamma_p \\frac{\\boldsymbol{\\tau}}{\\|\\boldsymbol{\\tau}\\|} = \\mathbf{0}$\n2. 原始可行性：$\\|\\boldsymbol{\\tau}\\| - \\mu\\lambda_n \\le 0$\n3. 对偶可行性：$\\gamma_p \\ge 0$\n4. 互补性：$\\gamma_p (\\|\\boldsymbol{\\tau}\\| - \\mu\\lambda_n) = 0$\n\n我们分析互补条件。\n- 如果我们假设解 $\\boldsymbol{\\tau}$ 位于 $\\mathcal{F}$ 的内部（$\\|\\boldsymbol{\\tau}\\|  \\mu\\lambda_n$），那么 $\\gamma_p$ 必须为 $0$。平稳性条件简化为 $\\boldsymbol{\\tau} - \\boldsymbol{\\lambda}_t^{\\mathrm{tr}} = \\mathbf{0}$，所以 $\\boldsymbol{\\tau} = \\boldsymbol{\\lambda}_t^{\\mathrm{tr}}$。这是一个有效解，当且仅当 $\\boldsymbol{\\lambda}_t^{\\mathrm{tr}}$ 本身满足约束，即 $\\|\\boldsymbol{\\lambda}_t^{\\mathrm{tr}}\\| \\le \\mu\\lambda_n$。这对应于 **粘滞情况**。\n- 如果我们假设解位于边界上（$\\|\\boldsymbol{\\tau}\\| = \\mu\\lambda_n$），那么我们可能有 $\\gamma_p  0$。平稳性条件 $\\boldsymbol{\\tau} - \\boldsymbol{\\lambda}_t^{\\mathrm{tr}} + \\gamma_p \\frac{\\boldsymbol{\\tau}}{\\mu\\lambda_n} = \\mathbf{0}$ 意味着 $\\boldsymbol{\\lambda}_t^{\\mathrm{tr}} = \\boldsymbol{\\tau}(1 + \\frac{\\gamma_p}{\\mu\\lambda_n})$。取范数，$\\|\\boldsymbol{\\lambda}_t^{\\mathrm{tr}}\\| = \\|\\boldsymbol{\\tau}\\|(1 + \\frac{\\gamma_p}{\\mu\\lambda_n}) = \\mu\\lambda_n(1 + \\frac{\\gamma_p}{\\mu\\lambda_n}) = \\mu\\lambda_n + \\gamma_p$。因此 $\\gamma_p = \\|\\boldsymbol{\\lambda}_t^{\\mathrm{tr}}\\| - \\mu\\lambda_n$。条件 $\\gamma_p  0$ 意味着这种情况适用于 $\\|\\boldsymbol{\\lambda}_t^{\\mathrm{tr}}\\|  \\mu\\lambda_n$ 时。解 $\\boldsymbol{\\tau}$ 与 $\\boldsymbol{\\lambda}_t^{\\mathrm{tr}}$ 共线，且范数为 $\\mu\\lambda_n$，所以 $\\boldsymbol{\\tau} = (\\mu\\lambda_n) \\frac{\\boldsymbol{\\lambda}_t^{\\mathrm{tr}}}{\\|\\boldsymbol{\\lambda}_t^{\\mathrm{tr}}\\|}$。这对应于 **滑移情况**。\n\n该最小化问题的解与回映算法的解完全相同，从而证明了它们的等价性。\n\n**4. 与全局 Newton 系统的耦合**\n\n推导出的算法 $\\boldsymbol{\\lambda}_t = \\boldsymbol{\\lambda}_t(\\Delta\\mathbf{u})$ 通过关系式 $\\Delta\\mathbf{u}_t = \\mathbf{B}_t \\Delta\\mathbf{u}$ 和 $\\boldsymbol{\\lambda}_t^{\\mathrm{tr}} = \\boldsymbol{\\lambda}_t^n + k_t \\Delta\\mathbf{u}_t$，为给定的增量全局位移 $\\Delta\\mathbf{u}$ 提供更新后的切向牵引力。在全局隐式求解器（例如 Newton-Raphson）中，目标是找到使全局残差向量 $\\mathbf{R}(\\Delta\\mathbf{u})$ 趋于零的 $\\Delta\\mathbf{u}$。对该残差的接触贡献为 $\\mathbf{R}_c = \\mathbf{B}_t^T \\boldsymbol{\\lambda}_t$。在每次 Newton 迭代中，都有一个 $\\Delta\\mathbf{u}$ 的估计值。回映算法用于计算相应的 $\\boldsymbol{\\lambda}_t$，然后将得到的力 $\\mathbf{B}_t^T \\boldsymbol{\\lambda}_t$ 组装到全局残差向量中。该项的线性化贡献于全局切向刚度矩阵，确保了 Newton 法的二次收敛性。\n\n**5. 数值计算**\n\n给定数据：\n$\\boldsymbol{\\lambda}_t^n = \\mathbf{0}$\n$\\lambda_n = 20000\\,\\text{N}$\n$\\mu = 0.3$\n$k_t = 1.0 \\times 10^7\\,\\text{N/m}$\n$\\Delta\\mathbf{u}_t = \\begin{pmatrix} 0.0008 \\\\ -0.0006 \\end{pmatrix}\\,\\text{m}$\n$\\mathbf{B}_t = \\begin{pmatrix} 1  0  0  -1  0  0 \\\\ 0  1  0  0  -1  0 \\end{pmatrix}$\n\n**步骤 1：计算试探切向牵引力 $\\boldsymbol{\\lambda}_t^{\\mathrm{tr}}$**\n$$\n\\boldsymbol{\\lambda}_t^{\\mathrm{tr}} = \\boldsymbol{\\lambda}_t^n + k_t \\Delta\\mathbf{u}_t = \\mathbf{0} + (1.0 \\times 10^7) \\begin{pmatrix} 0.0008 \\\\ -0.0006 \\end{pmatrix} = \\begin{pmatrix} 8000 \\\\ -6000 \\end{pmatrix}\\,\\text{N}\n$$\n\n**步骤 2：检查是否滑移**\n计算试探牵引力的范数：\n$$\n\\|\\boldsymbol{\\lambda}_t^{\\mathrm{tr}}\\| = \\sqrt{8000^2 + (-6000)^2} = \\sqrt{64000000 + 36000000} = \\sqrt{100000000} = 10000\\,\\text{N}\n$$\n计算摩擦极限（摩擦圆盘 $\\mathcal{F}$ 的半径）：\n$$\nR = \\mu\\lambda_n = 0.3 \\times 20000 = 6000\\,\\text{N}\n$$\n由于 $\\|\\boldsymbol{\\lambda}_t^{\\mathrm{tr}}\\| = 10000\\,\\text{N}  R = 6000\\,\\text{N}$，条件为滑移。\n\n**步骤 3：对滑移情况应用回映**\n更新后的切向牵引力 $\\boldsymbol{\\lambda}_t$ 通过将 $\\boldsymbol{\\lambda}_t^{\\mathrm{tr}}$ 径向投影到摩擦锥边界上得到：\n$$\n\\boldsymbol{\\lambda}_t = R \\frac{\\boldsymbol{\\lambda}_t^{\\mathrm{tr}}}{\\|\\boldsymbol{\\lambda}_t^{\\mathrm{tr}}\\|} = 6000 \\cdot \\frac{\\begin{pmatrix} 8000 \\\\ -6000 \\end{pmatrix}}{10000} = 6000 \\cdot \\begin{pmatrix} 0.8 \\\\ -0.6 \\end{pmatrix} = \\begin{pmatrix} 4800 \\\\ -3600 \\end{pmatrix}\\,\\text{N}\n$$\n\n**步骤 4：计算全局接触力向量**\n最终答案是对全局残差的接触力贡献，由 $\\mathbf{B}_t^T\\boldsymbol{\\lambda}_t$ 给出。首先，我们确定 $\\mathbf{B}_t$ 的转置：\n$$\n\\mathbf{B}_t^T = \\begin{pmatrix} 1  0 \\\\ 0  1 \\\\ 0  0 \\\\ -1  0 \\\\ 0  -1 \\\\ 0  0 \\end{pmatrix}\n$$\n现在，我们计算乘积：\n$$\n\\mathbf{B}_t^T \\boldsymbol{\\lambda}_t = \\begin{pmatrix} 1  0 \\\\ 0  1 \\\\ 0  0 \\\\ -1  0 \\\\ 0  -1 \\\\ 0  0 \\end{pmatrix} \\begin{pmatrix} 4800 \\\\ -3600 \\end{pmatrix} = \\begin{pmatrix} 1 \\cdot 4800 + 0 \\cdot (-3600) \\\\ 0 \\cdot 4800 + 1 \\cdot (-3600) \\\\ 0 \\\\ -1 \\cdot 4800 + 0 \\cdot (-3600) \\\\ 0 \\cdot 4800 + (-1) \\cdot (-3600) \\\\ 0 \\end{pmatrix} = \\begin{pmatrix} 4800 \\\\ -3600 \\\\ 0 \\\\ -4800 \\\\ 3600 \\\\ 0 \\end{pmatrix}\\,\\text{N}\n$$\n全局接触力向量以分量 $(4800, -3600, 0)$ 作用于节点 $\\mathrm{P}$，以分量 $(-4800, 3600, 0)$ 作用于节点 $\\mathrm{Q}$，这与 $\\mathbf{B}_t$ 的定义一致。最终答案是该向量，表示为一个行矩阵。", "answer": "$$\n\\boxed{\\begin{pmatrix} 4800  -3600  0  -4800  3600  0 \\end{pmatrix}}\n$$", "id": "3537768"}, {"introduction": "最后一步是将局部接触定律整合到全局求解器中，以解决完整的边界值问题。本练习 [@problem_id:3537740] 通过为一个一维接触问题编写半光滑牛顿法求解器，提供了宝贵的实践经验。您将有机会亲手实现一个求解器，用于求解接触力学中出现的完整非线性方程组，并探索数值正则化等实用技术对解的影响。", "problem": "考虑一个代表计算岩土力学中无摩擦单边接触问题的一维离散界面，该问题通过 Lagrange 乘子强制实施。设存在 $N$ 个节点自由度 $u \\in \\mathbb{R}^N$，用于描述沿界面的法向位移场。障碍物（刚性障碍物）的轮廓由 $h \\in \\mathbb{R}^N$ 给出，外部节点载荷为 $f \\in \\mathbb{R}^N$。离散弹性势能由二次型 $\\tfrac{1}{2} u^\\top K u - f^\\top u$ 定义，其中 $K \\in \\mathbb{R}^{N \\times N}$ 是一个对称正定刚度矩阵。该矩阵由标准的二阶导数有限差分模板构建，并在两端施加齐次 Dirichlet 边界条件。具体而言，$K$ 是一个三对角矩阵，对于内部索引，$K_{ii} = 2$、$K_{i,i-1} = -1$、$K_{i,i+1} = -1$。单边接触约束要求对所有 $i$ 满足非穿透条件 $g_i(u) = u_i - h_i \\ge 0$，并由 Lagrange 乘子 $\\lambda_i \\ge 0$ 强制实施 $g_i(u) \\ge 0$。控制条件是通过在单边约束下最小化能量推导出的 Karush-Kuhn-Tucker (KKT) 系统：\n- 平衡：$K u - f - \\lambda = 0$，\n- 不等式约束：$u - h \\ge 0$，$\\lambda \\ge 0$，\n- 互补性：对所有 $i$ 都有 $(u_i - h_i) \\lambda_i = 0$，这可以使用非线性互补问题 (NCP) 函数来表示。\n\n您将实现并比较两种接触实施策略：\n1. 通过 Fischer-Burmeister 函数 $\\phi(a,b) = \\sqrt{a^2 + b^2} - (a + b)$ 实现的标准非光滑互补性，当 $\\phi(a,b) = 0$ 时，该函数强制实施 $a \\ge 0$、$b \\ge 0$ 和 $a b = 0$。\n2. 通过 $\\epsilon$-光滑化的 Fischer-Burmeister 函数 $\\phi_\\epsilon(a,b) = \\sqrt{a^2 + b^2 + 2 \\epsilon} - (a + b)$ 实现的数值正则化（光滑化）互补性，其中 $\\epsilon  0$。\n\n从凸约束最小化和接触力学的基础出发，将平衡和互补性条件组合成半光滑系统\n$$\nF(u,\\lambda) =\n\\begin{bmatrix}\nK u - f - \\lambda \\\\\n\\phi_\\epsilon(u - h, \\lambda)\n\\end{bmatrix}\n= 0,\n$$\n其中第一个分块强制平衡，第二个分块为每个节点强制互补性。对于非光滑情况，设置 $\\epsilon = 0$；对于光滑情况，设置 $\\epsilon  0$。您必须使用带线搜索的半光滑 Newton 方法求解 $F(u,\\lambda) = 0$，确保在所有迭代中 $u - h \\ge 0$ 和 $\\lambda \\ge 0$ 均成立，并使用基于 $\\phi_\\epsilon$ 导数的广义雅可比矩阵：\n$$\n\\frac{\\partial \\phi_\\epsilon}{\\partial a} = \\frac{a}{\\sqrt{a^2 + b^2 + 2 \\epsilon}} - 1,\\quad\n\\frac{\\partial \\phi_\\epsilon}{\\partial b} = \\frac{b}{\\sqrt{a^2 + b^2 + 2 \\epsilon}} - 1,\n$$\n约定当 $a = 0$ 和 $b = 0$ 时，为保证数值鲁棒性，偏导数可取为 $-1$。$F$ 的雅可比矩阵则为\n$$\nJ(u,\\lambda) =\n\\begin{bmatrix}\nK  -I \\\\\n\\operatorname{diag}\\left(\\tfrac{\\partial \\phi_\\epsilon}{\\partial a}\\big|_{a=u-h,\\,b=\\lambda}\\right)  \\operatorname{diag}\\left(\\tfrac{\\partial \\phi_\\epsilon}{\\partial b}\\big|_{a=u-h,\\,b=\\lambda}\\right)\n\\end{bmatrix}.\n$$\n\n将障碍物轮廓 $h$ 定义为以界面中点为中心的对称高斯凸起：\n$$\nh_i = h_0 \\exp\\!\\left(-\\left(\\frac{i - m}{\\sigma_h}\\right)^2\\right), \\quad m = \\frac{N+1}{2},\n$$\n其中 $h_0  0$ 且 $\\sigma_h  0$，单位为节点数。将外部载荷 $f$ 定义为两个高斯边缘载荷之和，以促使两端附近产生开口：\n$$\nf_i = p \\left[\\exp\\!\\left(-\\left(\\frac{i - 1}{\\sigma_e}\\right)^2\\right) + \\exp\\!\\left(-\\left(\\frac{i - N}{\\sigma_e}\\right)^2\\right)\\right],\n$$\n其中 $p  0$ 且 $\\sigma_e  0$。这种加载方式在边缘附近产生开放间隙区域（$u_i - h_i  0$，$\\lambda_i = 0$），并在凸起附近产生接触区域（$u_i - h_i = 0$，$\\lambda_i  0$），从而形成 Lagrange 乘子趋于集中的边界。\n\n您的研究目标是检验通过 $\\epsilon$-光滑化进行的数值正则化是否能在不改变全局响应的情况下减少伪峰值乘子。量化指标如下：\n- 峰值乘子为 $\\max_i \\lambda_i$，\n- 全局响应为总反力 $R = \\sum_i \\lambda_i$。\n\n对于每个测试用例，计算非光滑解（$\\epsilon = 0$）和光滑解（指定的 $\\epsilon  0$），然后评估布尔谓词\n$$\n\\left[\\max_i \\lambda_i^{(\\epsilon)}  \\max_i \\lambda_i^{(0)}\\right] \\wedge \\left[\\frac{\\left|R^{(\\epsilon)} - R^{(0)}\\right|}{R^{(0)}} \\le \\text{tol}\\right],\n$$\n如果光滑化降低了峰值乘子，并将全局响应保持在指定容差 $\\text{tol}$（以小数表示，而非百分号）范围内，则该谓词为真。\n\n实现半光滑 Newton 方法，包含以下内容：\n- 初始化 $u^{(0)} = h$，$\\lambda^{(0)} = \\max(K u^{(0)} - f, 0)$，\n- 通过求解 $J \\Delta z = -F$ 得到 $\\Delta z$ 来进行更新，然后通过线搜索缩放来强制 $u - h \\ge 0$ 和 $\\lambda \\ge 0$ 同时减小残差范数，\n- 当 $\\|F\\|_2 \\le \\tau$ 时收敛，其中 $\\tau$ 为一个小容差。\n\n所有测试均使用以下固定参数：$h_0 = 1.0$，$\\sigma_h = N/10$，$\\sigma_e = N/12$，Newton 容差 $\\tau = 10^{-10}$，每次求解的迭代次数上限为 $200$。\n\n测试套件：\n- 用例 1：$N = 64$，$\\epsilon = 10^{-2}$，$p = 0.5$，$\\text{tol} = 0.02$。\n- 用例 2：$N = 64$，$\\epsilon = 10^{-6}$，$p = 0.5$，$\\text{tol} = 0.001$。\n- 用例 3：$N = 64$，$\\epsilon = 10^{-1}$，$p = 0.5$，$\\text{tol} = 0.02$。\n- 用例 4：$N = 128$，$\\epsilon = 10^{-2}$，$p = 0.5$，$\\text{tol} = 0.02$。\n- 用例 5：$N = 16$，$\\epsilon = 10^{-2}$，$p = 0.5$，$\\text{tol} = 0.02$。\n\n您的程序应生成单行输出，其中包含用方括号括起来的逗号分隔的结果列表（例如，`[result1,result2,result3,result4,result5]`）。每个结果都必须是一个布尔值，指示谓词对于相应的测试用例是否成立。", "solution": "用户提供了一个完整、科学上合理且适定的问题陈述。该问题是计算接触力学（计算岩土力学的一个子领域）中的一个标准练习。它要求实现一个半光滑 Newton 方法来求解一个无摩擦单边接触问题，并比较标准非光滑公式与正则化（光滑）公式的结果。所有参数和控制方程都已明确定义。因此，着手求解是合适的。\n\n### 基于原理的求解推导\n\n当前的问题是在一组不等式约束下，最小化离散弹性势能。这是一个经典的凸约束优化问题。\n\n**1. 变分公式和 KKT 条件**\n\n系统的总势能 $\\Pi(u)$ 是弹性应变能与外力势能之和：\n$$\n\\Pi(u) = \\frac{1}{2} u^\\top K u - f^\\top u\n$$\n其中 $u \\in \\mathbb{R}^N$ 是节点位移向量，$K \\in \\mathbb{R}^{N \\times N}$ 是对称正定刚度矩阵，$f \\in \\mathbb{R}^N$ 是外力向量。\n\n接触是单边的，意味着节点不能穿透由轮廓 $h \\in \\mathbb{R}^N$ 定义的刚性障碍物。这施加了一组不等式约束：\n$$\ng_i(u) = u_i - h_i \\ge 0 \\quad \\forall i \\in \\{1, \\dots, N\\}\n$$\n问题在于找到位移场 $u$，使其在 $g_i(u) \\ge 0$ 的约束下最小化 $\\Pi(u)$。\n\n我们引入 Lagrange 乘子 $\\lambda \\in \\mathbb{R}^N$ 来强制实施这些约束。Lagrangian 泛函 $L(u, \\lambda)$ 为：\n$$\nL(u, \\lambda) = \\Pi(u) - \\sum_{i=1}^N \\lambda_i g_i(u) = \\frac{1}{2} u^\\top K u - f^\\top u - \\lambda^\\top(u - h)\n$$\n约束最小化问题的解必须满足 Karush-Kuhn-Tucker (KKT) 条件，这些条件代表了最优性的一阶必要条件：\n1.  **平稳性（平衡）：** Lagrangian 泛函相对于主变量 ($u$) 的梯度必须为零。\n    $$\n    \\nabla_u L(u, \\lambda) = K u - f - \\lambda = 0\n    $$\n    这是离散平衡方程，其中 $\\lambda$ 代表接触反力。\n2.  **原始可行性：** 位移约束必须得到满足。\n    $$\n    u_i - h_i \\ge 0 \\quad \\forall i\n    $$\n3.  **对偶可行性：** Lagrange 乘子（接触力）必须为非负，因为接触只能是压缩性的。\n    $$\n    \\lambda_i \\ge 0 \\quad \\forall i\n    $$\n4.  **互补性：** 对于每个节点，要么节点未接触（间隙打开，$u_i - h_i  0$）且接触力为零（$\\lambda_i = 0$），要么节点处于接触状态（间隙闭合，$u_i - h_i = 0$）且可能存在非零接触力（$\\lambda_i \\ge 0$）。这由互补性条件捕获：\n    $$\n    \\lambda_i (u_i - h_i) = 0 \\quad \\forall i\n    $$\n\n**2. 非线性互补问题 (NCP) 公式**\n\n涉及不等式的三个条件（原始可行性、对偶可行性和互补性）可以为每个节点 $i$ 紧凑地写为：\n$$\nu_i - h_i \\ge 0, \\quad \\lambda_i \\ge 0, \\quad (u_i - h_i) \\lambda_i = 0\n$$\n这是一个非线性互补问题 (NCP)。一种表达此问题的强大方法是使用 NCP 函数 $\\phi(a, b)$，其性质为 $\\phi(a, b) = 0 \\iff a \\ge 0, b \\ge 0, ab = 0$。\n\n该问题指定了 Fischer-Burmeister (FB) 函数：\n$$\n\\phi(a, b) = \\sqrt{a^2 + b^2} - (a + b)\n$$\n待求解的方程组由平衡方程和使用 FB 函数表示的所有节点的互补性条件组成。令 $z = [u^\\top, \\lambda^\\top]^\\top$ 为未知量的组合向量。该系统为 $F(z) = 0$，其中：\n$$\nF(u, \\lambda) = \\begin{bmatrix} K u - f - \\lambda \\\\ \\phi(u - h, \\lambda) \\end{bmatrix} = 0\n$$\n第二个分块 $\\phi(u - h, \\lambda)$ 是一个向量，其第 $i$ 个分量是 $\\phi(u_i - h_i, \\lambda_i)$。\n\nFB 函数在 $(a, b) = (0, 0)$ 处是非光滑的（不可微）。这种情况发生在接触和非接触之间的过渡点。这种不可微性妨碍了标准 Newton 方法的使用。\n\n**3. 半光滑 Newton 方法**\n\n半光滑 Newton 方法是 Newton 方法在非光滑函数上的扩展。它用广义雅可比矩阵（或 B-次微分）的一个成员替换标准雅可比矩阵。\n\n迭代更新为：\n$$\nJ(z^{(k)}) \\Delta z^{(k)} = -F(z^{(k)})\n$$\n$$\nz^{(k+1)} = z^{(k)} + \\alpha^{(k)} \\Delta z^{(k)}\n$$\n其中 $J$ 是 $F$ 的广义雅可比矩阵，$\\alpha^{(k)}$ 是由线搜索确定的步长。\n\n该问题还引入了一个用于正则化的光滑 FB 函数：\n$$\n\\phi_\\epsilon(a, b) = \\sqrt{a^2 + b^2 + 2\\epsilon} - (a+b) \\quad (\\epsilon  0)\n$$\n该函数处处连续可微，将问题转化为一个可用标准 Newton 方法求解的非线性系统。当 $\\epsilon \\to 0$ 时，光滑问题的解逼近原始非光滑问题的解。本研究旨在调查这种光滑化的效果。\n\n系统 $F(u,\\lambda)=0$（使用光滑或非光滑函数）的雅可比矩阵 $J$ 具有 $2 \\times 2$ 的分块结构：\n$$\nJ(u,\\lambda) = \\frac{\\partial F}{\\partial z} = \\begin{bmatrix} \\frac{\\partial (Ku-f-\\lambda)}{\\partial u}  \\frac{\\partial (Ku-f-\\lambda)}{\\partial \\lambda} \\\\ \\frac{\\partial \\phi_\\epsilon}{\\partial u}  \\frac{\\partial \\phi_\\epsilon}{\\partial \\lambda} \\end{bmatrix}\n$$\n计算各分块的偏导数可得：\n- $\\frac{\\partial (Ku-f-\\lambda)}{\\partial u} = K$\n- $\\frac{\\partial (Ku-f-\\lambda)}{\\partial \\lambda} = -I$ (其中 $I$ 是单位矩阵)\n- $\\frac{\\partial \\phi_\\epsilon(u-h, \\lambda)}{\\partial u} = \\operatorname{diag}\\left( \\frac{\\partial \\phi_\\epsilon(u_i-h_i, \\lambda_i)}{\\partial(u_i-h_i)} \\right) = \\operatorname{diag}\\left( \\frac{u_i-h_i}{\\sqrt{(u_i-h_i)^2 + \\lambda_i^2 + 2\\epsilon}} - 1 \\right)$\n- $\\frac{\\partial \\phi_\\epsilon(u-h, \\lambda)}{\\partial \\lambda} = \\operatorname{diag}\\left( \\frac{\\partial \\phi_\\epsilon(u_i-h_i, \\lambda_i)}{\\partial\\lambda_i} \\right) = \\operatorname{diag}\\left( \\frac{\\lambda_i}{\\sqrt{(u_i-h_i)^2 + \\lambda_i^2 + 2\\epsilon}} - 1 \\right)$\n\n对于非光滑情况（$\\epsilon=0$），在 $u_i-h_i=0$ 和 $\\lambda_i=0$ 的点，分母变为零。在这些点，我们按照指示使用广义雅可比矩阵中的一个特定元素：偏导数取为 $-1$。\n\n**4. 算法实现**\n\n对于每个测试用例，算法按以下步骤进行：\n1.  **设置：** 对于给定的 $N$，根据所提供的公式构造刚度矩阵 $K$、障碍物轮廓 $h$ 和外载荷向量 $f$。矩阵 $K$ 是一个三对角矩阵，主对角线上元素为 $2$，次对角线上元素为 $-1$。\n2.  **初始化：** 一个鲁棒的初始猜测至关重要。我们从接触边界上的位移开始，$u^{(0)}=h$。然后，我们计算如果所有节点都处于接触状态下维持平衡所需的反作用力：$\\lambda_{guess} = K u^{(0)} - f$。由于接触力必须为非负，我们将其投影到可行集上：$\\lambda^{(0)} = \\max(0, \\lambda_{guess})$。这确保了初始猜测的原始和对偶可行性（关于非负性）。\n3.  **Newton 迭代：**\n    a.  **计算残差：** 计算残差向量 $F(u^{(k)}, \\lambda^{(k)})$。\n    b.  **检查收敛：** 如果 L2-范数 $\\|F\\|_2$ 低于容差 $\\tau=10^{-10}$，则解已收敛。\n    c.  **组装雅可比矩阵：** 使用指定的导数构造雅可比矩阵 $J(u^{(k)}, \\lambda^{(k)})$。当 $\\epsilon=0$、$u_i-h_i=0$ 和 $\\lambda_i=0$ 时，需要特别处理奇异情况。\n    d.  **求解线性系统：** 求解线性系统 $J \\Delta z = -F$ 以找到 Newton 搜索方向 $\\Delta z = [\\Delta u^\\top, \\Delta \\lambda^\\top]^\\top$。\n    e.  **线搜索：** 执行回溯线搜索以找到步长 $\\alpha \\in (0, 1]$。从 $\\alpha=1$ 开始。在每个试探步，验证新的迭代值 $u^{(k+1)} = u^{(k)} + \\alpha \\Delta u$ 和 $\\lambda^{(k+1)} = \\lambda^{(k)} + \\alpha \\Delta \\lambda$ 是否满足非负约束 $u^{(k+1)} - h \\ge 0$ 和 $\\lambda^{(k+1)} \\ge 0$。同时，确保该步能使残差范数充分下降 $\\|F(z^{(k+1)})\\|_2  \\|F(z^{(k)})\\|_2$。如果条件不满足，则减小 $\\alpha$（例如，$\\alpha \\leftarrow \\alpha/2$）并重复。\n    f.  **更新：** 更新解向量 $u^{(k+1)}$ 和 $\\lambda^{(k+1)}$ 并进入下一次迭代。\n4.  **分析：** 在获得非光滑情况（$\\epsilon=0$ 时的 $\\lambda^{(0)}$）和光滑情况（$\\epsilon0$ 时的 $\\lambda^{(\\epsilon)}$）的收敛解后，计算所需的量：峰值乘子 $\\max_i \\lambda_i$ 和总反力 $R = \\sum_i \\lambda_i$。评估问题陈述中指定的布尔谓词，以确定光滑化是否在保持全局响应的同时减小了峰值乘子。对五个测试用例中的每一个重复此过程。", "answer": "$$\n\\boxed{\\text{[True,True,False,True,True]}}\n$$", "id": "3537740"}]}